{
    "version": "5.6.4",
    "description": "Comic and manga converter for ebook readers.",
    "homepage": "https://github.com/ciromattia/kcc",
    "license": "ISC",
    "depends": "extras/kindlegen",
    "architecture": {
        "64bit": {
            "url": "https://kcc.iosphe.re/Windows/KindleComicConverter_win_5.6.4.exe",
            "hash": "e3324219d33f0b828d22a8f14551fd10c061e0f952b975f2686e62b005d2a3e9",
            "shortcuts": [
                [
                    "KCC.exe",
                    "Kindle Comic Converter"
                ]
            ]
        }
    },
    "innosetup": true,
    "checkver": "github",
    "autoupdate": {
        "architecture": {
            "64bit": {
                "url": "https://kcc.iosphe.re/Windows/KindleComicConverter_win_$version.exe"
            }
        }
    }
}
